trex/__init__.py
trex/__main__.py
trex/capture.py
trex/cli.py
trex/clipboard.py
trex/config.py
trex/ocr.py
trex/ocr_tesseract.py
trex/qr_utils.py
trex/url_utils.py
trex/utils.py
trex_ocr-1.1.0.dist-info/METADATA
trex_ocr-1.1.0.dist-info/WHEEL
trex_ocr-1.1.0.dist-info/entry_points.txt
trex_ocr-1.1.0.dist-info/top_level.txt
trex_ocr-1.1.0.dist-info/RECORD
