Metadata-Version: 2.1
Name: trex-ocr
Version: 1.1.0
Summary: Lightning-fast OCR and QR code reader for Wayland/Linux. Tesseract by default, with optional AI-powered mode.
Author-email: amebalabs <team@amebalabs.com>
Project-URL: Homepage, https://github.com/amebalabs/trex-linux
Project-URL: Repository, https://github.com/amebalabs/trex-linux
Project-URL: Issues, https://github.com/amebalabs/trex-linux/issues
Keywords: ocr,tesseract,easyocr,wayland,linux,screenshot,text-recognition,fast-ocr,clipboard,qr-code
Classifier: Development Status :: 5 - Production/Stable
Classifier: Environment :: Console
Classifier: Intended Audience :: End Users/Desktop
Classifier: License :: OSI Approved :: MIT License
Classifier: Operating System :: POSIX :: Linux
Classifier: Programming Language :: Python :: 3
Classifier: Programming Language :: Python :: 3.8
Classifier: Programming Language :: Python :: 3.9
Classifier: Programming Language :: Python :: 3.10
Classifier: Programming Language :: Python :: 3.11
Classifier: Programming Language :: Python :: 3.12
Classifier: Topic :: Text Processing
Classifier: Topic :: Utilities
Classifier: Environment :: X11 Applications
Classifier: Environment :: GPU
Requires-Python: >=3.8
Requires-Dist: click >=8.0
Requires-Dist: Pillow >=9.0
Requires-Dist: numpy >=1.19.0
Requires-Dist: opencv-python >=4.5
Requires-Dist: pyzbar >=0.1.9
Provides-Extra: accurate
Requires-Dist: easyocr >=1.7.0 ; extra == 'accurate'
Requires-Dist: opencv-python >=4.5 ; extra == 'accurate'
Requires-Dist: torch >=1.9.0 ; extra == 'accurate'
Requires-Dist: torchvision >=0.10.0 ; extra == 'accurate'
Provides-Extra: dev
Requires-Dist: pytest >=7.0 ; extra == 'dev'
Requires-Dist: pytest-cov >=4.0 ; extra == 'dev'
Requires-Dist: black >=22.0 ; extra == 'dev'
Requires-Dist: flake8 >=5.0 ; extra == 'dev'
Requires-Dist: mypy >=0.990 ; extra == 'dev'
Requires-Dist: pre-commit >=2.20 ; extra == 'dev'
Provides-Extra: gpu
Requires-Dist: torch >=1.9.0 ; extra == 'gpu'
Requires-Dist: torchvision >=0.10.0 ; extra == 'gpu'
